{"cameraMode":{"drawMode":0,"name":"Shaded","section":"Shading Mode"},"sceneLighting":true,"audioPlay":false,"sceneViewState":{"m_AlwaysRefresh":false,"showFog":true,"showSkybox":true,"showFlares":true,"showImageEffects":true,"showParticleSystems":true,"showVisualEffectGraphs":true,"m_FxEnabled":true},"in2DMode":false,"pivot":{"x":19.933900833129884,"y":10.986444473266602,"z":16.296350479125978},"rotation":{"x":0.12865708768367768,"y":-0.7598615288734436,"z":0.15839225053787232,"w":0.6172585487365723},"size":14.138265609741211,"orthographic":false}