{"cameraMode":{"drawMode":0,"name":"Shaded","section":"Shading Mode"},"sceneLighting":true,"audioPlay":false,"sceneViewState":{"m_AlwaysRefresh":false,"showFog":true,"showSkybox":true,"showFlares":true,"showImageEffects":true,"showParticleSystems":true,"showVisualEffectGraphs":true,"m_FxEnabled":true},"in2DMode":false,"pivot":{"x":0.18907403945922852,"y":5.248476028442383,"z":14.622934341430664},"rotation":{"x":-0.023567404597997667,"y":0.9544086456298828,"z":-0.07833939790725708,"w":-0.2870987057685852},"size":11.424749374389649,"orthographic":false}